aws_ir_plugins/__init__.py
aws_ir_plugins/_version.py
aws_ir_plugins/disableaccess_key.py
aws_ir_plugins/examineracl_host.py
aws_ir_plugins/gather_host.py
aws_ir_plugins/isolate_host.py
aws_ir_plugins/revokests_key.py
aws_ir_plugins/snapshotdisks_host.py
aws_ir_plugins/stop_host.py
aws_ir_plugins/tag_host.py
aws_ir_plugins/templates/deny-sts-before-time.json.j2
aws_ir_plugins-0.0.3.dist-info/METADATA
aws_ir_plugins-0.0.3.dist-info/RECORD
aws_ir_plugins-0.0.3.dist-info/WHEEL
aws_ir_plugins-0.0.3.dist-info/top_level.txt
