Metadata-Version: 2.1
Name: aws-ir-plugins
Version: 0.0.3
Summary: AWS Incident Response ToolKit Core Supported plugins
Home-page: https://github.com/ThreatResponse/aws_ir_plugins
Author: Andrew Krug, Alex McCormack, Joel Ferrier, Jeff Parr
Author-email: andrewkrug@gmail.com,developer@amccormack.net,joel@ferrier.io,jp@ephemeralsystems.com
License: MIT
Platform: UNKNOWN
Requires-Dist: boto3 (>=1.3.0)
Requires-Dist: requests
Requires-Dist: jinja2
